<?xml version="1.0" encoding="UTF-8"?>
<jcr:root xmlns:dc="http://purl.org/dc/elements/1.1/" xmlns:sling="http://sling.apache.org/jcr/sling/1.0" xmlns:dam="http://www.day.com/dam/1.0" xmlns:cq="http://www.day.com/jcr/cq/1.0" xmlns:jcr="http://www.jcp.org/jcr/1.0" xmlns:mix="http://www.jcp.org/jcr/mix/1.0" xmlns:nt="http://www.jcp.org/jcr/nt/1.0"
    jcr:mixinTypes="[mix:referenceable]"
    jcr:primaryType="dam:Asset"
    jcr:uuid="c633cbb2-ebfa-4fd5-9c8d-a3193ba41775">
    <jcr:content
        cq:name="aloha-spirits-in-northern-norway"
        cq:parentPath="/content/dam/we-retail/articles"
        dam:assetID="985dd492-4077-498e-a06b-bad315002966"
        dam:compoundType="contentFragment"
        dam:relativePath="we-retail/articles/aloha-spirits-in-northern-norway"
        jcr:lastModified="{Date}2016-02-29T19:30:04.211+01:00"
        jcr:lastModifiedBy="admin"
        jcr:primaryType="dam:AssetContent"
        jcr:title="Aloha spirits in Northern Norway">
        <metadata
            cq:tags="[we-retail:activity/surfing,we-retail:season/winter]"
            dam:extracted="{Date}2016-02-29T19:30:04.126+01:00"
            dam:sha1="4fad4814bb24feb2051254a69f1534cf56f2ac09"
            dam:size="{Long}5675"
            dc:format="text/html"
            dc:modified="{Date}2016-02-25T23:53:59.904+01:00"
            jcr:lastModified="{Date}2016-02-29T19:18:03.275+01:00"
            jcr:lastModifiedBy="admin"
            jcr:mixinTypes="[cq:Taggable]"
            jcr:primaryType="nt:unstructured"/>
        <related jcr:primaryType="nt:unstructured"/>
        <usages
            dam:score="{Long}1"
            jcr:primaryType="nt:unstructured"
            usedBy="[aem]">
            <aem
                jcr:primaryType="nt:unstructured"
                count="{Long}1"
                lastUsed="{Date}2016-02-25T23:56:30.824+01:00"/>
        </usages>
    </jcr:content>
    <associated
        jcr:primaryType="nt:unstructured"
        sling:resourceType="sling/collection">
        <sling:members
            jcr:primaryType="nt:unstructured"
            sling:resources="[/content/dam/collections/we-retail/aloha_spirits_innorthernnorway]">
            <aloha_spirits_innorthernnorway
                jcr:primaryType="nt:unstructured"
                sling:resource="/content/dam/collections/we-retail/aloha_spirits_innorthernnorway"/>
        </sling:members>
    </associated>
    <model
        jcr:description="A simple fragment, containing one single element and no predefined variations"
        jcr:primaryType="nt:unstructured"
        jcr:title="Simple Fragment"
        precreateElements="{Boolean}true"
        version="{Long}1">
        <elements jcr:primaryType="nt:unstructured">
            <main
                jcr:primaryType="nt:unstructured"
                jcr:title="Main"
                defaultContent=""
                name="main"/>
        </elements>
        <variations jcr:primaryType="nt:unstructured">
            <teaser
                jcr:description=""
                jcr:primaryType="nt:unstructured"
                jcr:title="Teaser"
                name="teaser"/>
        </variations>
    </model>
</jcr:root>
